voxelfuse/__init__.py
voxelfuse/gcode_tools.py
voxelfuse/materials.py
voxelfuse/mesh.py
voxelfuse/periodic.py
voxelfuse/plot.py
voxelfuse/primitives.py
voxelfuse/simulation.py
voxelfuse/voxel_model.py
voxelfuse/utils/LICENSE_VoxCad.txt
voxelfuse/utils/LICENSE_gmsh.txt
voxelfuse/utils/LICENSE_voxelyze.txt
voxelfuse/utils/VoxCad
voxelfuse/utils/VoxCad.exe
voxelfuse/utils/gmsh
voxelfuse/utils/gmsh.exe
voxelfuse/utils/onelab.py
voxelfuse/utils/voxelyze
voxelfuse/utils/voxelyze.exe
voxelfuse_examples/__init__.py
voxelfuse-1.2.8.dist-info/LICENSE.md
voxelfuse-1.2.8.dist-info/METADATA
voxelfuse-1.2.8.dist-info/WHEEL
voxelfuse-1.2.8.dist-info/top_level.txt
voxelfuse-1.2.8.dist-info/RECORD
