Metadata-Version: 2.1
Name: voxelfuse
Version: 1.2.8
Summary: A toolkit for processing 3D components made with mixtures of materials and multiple manufacturing processes
Home-page: https://github.com/cdbrauer/VoxelFuse
Author: Cole Brauer
License: UNKNOWN
Platform: UNKNOWN
Classifier: Programming Language :: Python :: 3
Classifier: License :: OSI Approved :: GNU General Public License v3 (GPLv3)
Classifier: Operating System :: OS Independent
License-File: LICENSE.md
Requires-Dist: numpy (>=1.20.3)
Requires-Dist: scipy (>=1.6.3)
Requires-Dist: pyqt5 (>=5.15.4)
Requires-Dist: pyqtgraph (>=0.12.1)
Requires-Dist: pyopengl (>=3.1.5)
Requires-Dist: py-vox-io (>=0.1)
Requires-Dist: meshio (>=4.4.3)
Requires-Dist: numba (>=0.53.1)
Requires-Dist: tqdm (>=4.60.0)
Requires-Dist: k3d (>=2.9.4)
Requires-Dist: PyMCubes (>=0.1.2)
Requires-Dist: quad-mesh-simplify (>=1.1.4)
